hera_cal/__init__.py
hera_cal/_cli_tools.py
hera_cal/_version.py
hera_cal/abscal.py
hera_cal/apply_cal.py
hera_cal/autos.py
hera_cal/chunker.py
hera_cal/datacontainer.py
hera_cal/delay_filter.py
hera_cal/flag_utils.py
hera_cal/frf.py
hera_cal/io.py
hera_cal/lstbin.py
hera_cal/noise.py
hera_cal/nucal.py
hera_cal/red_groups.py
hera_cal/redcal.py
hera_cal/reflections.py
hera_cal/smooth_cal.py
hera_cal/tempcal.py
hera_cal/types.py
hera_cal/utils.py
hera_cal/vis_clean.py
hera_cal/data/2458043.yaml
hera_cal/data/2458044.yaml
hera_cal/data/2458045.yaml
hera_cal/data/PyGSM_Jy_downselect.uvh5
hera_cal/data/__init__.py
hera_cal/data/efield_test_nside16.beamfits
hera_cal/data/example_filter_params.yaml
hera_cal/data/fr_unittest_beam.beamfits
hera_cal/data/fr_unittest_data.uvh5
hera_cal/data/fr_unittest_data_ds.uvh5
hera_cal/data/fr_unnittest_beam.beamfits
hera_cal/data/hera_antpos.yaml
hera_cal/data/red_averaging_conjugate_tester_0.uvh5
hera_cal/data/red_averaging_conjugate_tester_1.uvh5
hera_cal/data/red_averaging_conjugate_tester_2.uvh5
hera_cal/data/zen.2458043.12552.HH.uvA.omni.calfits
hera_cal/data/zen.2458043.12552.xx.HH.uvA.vis.uvfits
hera_cal/data/zen.2458043.12552.xx.HH.uvORA.abs.calfits
hera_cal/data/zen.2458043.12552.xx.HH.uvORA.dly.calfits
hera_cal/data/zen.2458043.40141.xx.HH.XRAA.abs.calfits
hera_cal/data/zen.2458043.40141.xx.HH.XRAA.uncalibrated.uvh5
hera_cal/data/zen.2458043.40141.xx.HH.XRAA.unity_gains.abs.calfits
hera_cal/data/zen.2458043.40141.xx.HH.XRAA.uvh5
hera_cal/data/zen.2458043.40887.xx.HH.XRAA.uvh5
hera_cal/data/zen.2458043.41632.xx.HH.XRAA.uvh5
hera_cal/data/zen.2458044.40141.xx.HH.XRAA.uvh5
hera_cal/data/zen.2458044.40886.xx.HH.XRAA.uvh5
hera_cal/data/zen.2458044.41632.xx.HH.XRAA.uvh5
hera_cal/data/zen.2458045.40140.xx.HH.XRAA.uvh5
hera_cal/data/zen.2458045.40886.xx.HH.XRAA.uvh5
hera_cal/data/zen.2458045.41632.xx.HH.XRAA.uvh5
hera_cal/data/zen.2458098.43124.downsample.uvh5
hera_cal/data/zen.2458098.43124.subband.uvh5
hera_calibration-3.7.7.dist-info/licenses/LICENSE
hera_calibration-3.7.7.dist-info/METADATA
hera_calibration-3.7.7.dist-info/WHEEL
hera_calibration-3.7.7.dist-info/top_level.txt
hera_calibration-3.7.7.dist-info/RECORD
