Metadata-Version: 2.4
Name: hera-calibration
Version: 3.7.7
Summary: A collection of calibration routines to run on the HERA instrument.
Author: HERA Team
License: BSD
Classifier: Development Status :: 4 - Beta
Classifier: Intended Audience :: Science/Research
Classifier: License :: OSI Approved
Classifier: License :: OSI Approved :: MIT License
Classifier: Natural Language :: English
Classifier: Programming Language :: Python :: 3
Classifier: Programming Language :: Python :: 3 :: Only
Classifier: Topic :: Scientific/Engineering :: Astronomy
Classifier: Topic :: Scientific/Engineering :: Physics
Requires-Python: >=3.9
License-File: LICENSE
Requires-Dist: numpy>=1.10
Requires-Dist: scipy>=1.9.0
Requires-Dist: h5py
Requires-Dist: hdf5plugin
Requires-Dist: astropy
Requires-Dist: astropy-healpix
Requires-Dist: pyuvdata>=3.2
Requires-Dist: linsolve
Requires-Dist: hera_qm>=2.2.0
Requires-Dist: scikit-learn
Requires-Dist: hera-filters
Requires-Dist: line_profiler
Requires-Dist: aipy
Requires-Dist: rich
Requires-Dist: jax
Requires-Dist: jaxlib
Requires-Dist: optax
Requires-Dist: attrs
Requires-Dist: frozendict
Requires-Dist: toml
Provides-Extra: dev
Requires-Dist: pytest; extra == "dev"
Requires-Dist: pre-commit; extra == "dev"
Requires-Dist: pytest-cov; extra == "dev"
Requires-Dist: hera_sim>=4.3.0; extra == "dev"
Requires-Dist: pytest-xdist; extra == "dev"
Requires-Dist: hypothesis; extra == "dev"
Requires-Dist: ruff; extra == "dev"
Dynamic: license-file
